naturalpay/__init__.py
naturalpay/__main__.py
naturalpay/_http.py
naturalpay/_sync_client.py
naturalpay/client.py
naturalpay/exceptions.py
naturalpay/mcp/__init__.py
naturalpay/mcp/cli.py
naturalpay/mcp/server.py
naturalpay/models.py
naturalpay/py.typed
naturalpay-0.0.4.dist-info/WHEEL
naturalpay-0.0.4.dist-info/entry_points.txt
naturalpay-0.0.4.dist-info/METADATA
naturalpay-0.0.4.dist-info/RECORD
