Metadata-Version: 2.4
Name: naturalpay
Version: 0.0.4
Summary: Natural Payments SDK
Keywords: payments,ai,agents,mcp,llm
Author: Natural
Author-email: Natural <walt@natural.co>
License-Expression: MIT
Classifier: Development Status :: 3 - Alpha
Classifier: Intended Audience :: Developers
Classifier: License :: OSI Approved :: MIT License
Classifier: Programming Language :: Python :: 3
Classifier: Programming Language :: Python :: 3.12
Classifier: Programming Language :: Python :: 3.13
Requires-Dist: fastmcp>=2,<3
Requires-Dist: httpx>=0.28.1
Requires-Dist: openai>=2.14.0
Requires-Dist: pydantic>=2.12.5
Requires-Dist: pytest>=8.0 ; extra == 'dev'
Requires-Dist: pytest-asyncio>=0.24 ; extra == 'dev'
Requires-Dist: pytest-cov>=4.0 ; extra == 'dev'
Requires-Python: >=3.12
Project-URL: Documentation, https://docs.natural.co
Project-URL: Homepage, https://natural.co
Project-URL: Repository, https://github.com/natural-co/naturalpay-python
Provides-Extra: dev
